{
	"sources" : 
	[
		{
			"file" : "/Users/mac/Desktop/OpenCV-WorkSpace/opencv-4.7.0/opencv_contrib-4.7.0/modules/plot/include/opencv2/plot.hpp",
			"labels" : 
			[
				"Extra",
				"opencv_plot",
				"Module"
			]
		},
		{
			"file" : "/Users/mac/Desktop/OpenCV-WorkSpace/opencv-4.7.0/opencv_contrib-4.7.0/modules/plot/src/plot.cpp",
			"labels" : 
			[
				"Extra",
				"opencv_plot",
				"Module"
			]
		},
		{
			"file" : "/Users/mac/Desktop/OpenCV-WorkSpace/opencv-4.7.0/opencv_contrib-4.7.0/modules/plot/src/precomp.hpp",
			"labels" : 
			[
				"Extra",
				"opencv_plot",
				"Module"
			]
		},
		{
			"file" : "/Users/mac/Desktop/OpenCV-WorkSpace/opencv-4.7.0/build/cvconfig.h"
		},
		{
			"file" : "/Users/mac/Desktop/OpenCV-WorkSpace/opencv-4.7.0/build/opencv2/opencv_modules.hpp"
		}
	],
	"target" : 
	{
		"labels" : 
		[
			"Extra",
			"opencv_plot",
			"Module"
		],
		"name" : "opencv_plot"
	}
}